[
  {
    "route": "#/",
    "access": "all"
  },
  {
    "route": "#/about",
    "access": [
      "unauthorized",
      "user"
    ]
  },
  {
    "route": "#/start",
    "access": [
      "unauthorized",
      "user"
    ]
  },
  {
    "route": "#/question",
    "access": [
      "unauthorized",
      "user"
    ]
  },
  {
    "route": "#/login",
    "access": [
      "unauthorized"
    ]
  },
  {
    "route": "#/admin/questions",
    "access": [
      "admin"
    ]
  },
  {
    "route": "#/admin/questions/add",
    "access": [
      "admin"
    ]
  },
  {
    "route": "#/logout",
    "access": [
      "admin",
      "user"
    ]
  }
]